{"title":"Glossaire CCNA 200-301","markdown":{"yaml":{"title":"Glossaire CCNA 200-301","description":"Environ 220 termes — protocoles, commandes, acronymes et concepts clés classés par ordre alphabétique"},"headingText":"A","headingAttr":{"id":"sec-glossaire-a","classes":[],"keyvalue":[]},"containsRefs":false,"markdown":"\n\n\n**AAA (Authentication, Authorization, Accounting)** — Cadre centralisant l'authentification (qui êtes-vous ?), l'autorisation (que pouvez-vous faire ?) et la traçabilité (qu'avez-vous fait ?) des accès réseau. _(Module 2, Topic 2.8 · Module 5, Topic 5.8)_\n\n**ACE (Access Control Entry)** — Règle individuelle dans une ACL, spécifiant une action `permit` ou `deny` pour un trafic correspondant à des critères donnés. _(Module 5, Topic 5.6)_\n\n**ACI (Application Centric Infrastructure)** — Solution SDN Cisco pour datacenter avec le contrôleur APIC et l'overlay VXLAN. _(Module 6, Topic 6.3)_\n\n**ACL (Access Control List)** — Liste ordonnée de règles filtrant le trafic réseau sur la base d'adresses IP, de ports et de protocoles. _(Module 5, Topic 5.6 · Module 4, Topic 4.1)_\n\n**AES-CCMP** — Algorithme de chiffrement utilisé par WPA2 (Advanced Encryption Standard – Counter Mode with CBC-MAC Protocol, 128 bits). _(Module 1, Topic 1.11 · Module 5, Topic 5.9)_\n\n**AES-GCMP** — Algorithme de chiffrement utilisé par WPA3 (AES – Galois/Counter Mode Protocol, 128/256 bits). _(Module 5, Topic 5.9)_\n\n**AH (Authentication Header)** — Protocole IPsec (IP Protocol 51) fournissant l'intégrité et l'authentification des paquets, sans chiffrement. _(Module 5, Topic 5.5)_\n\n**Ansible** — Outil de gestion de configuration agentless utilisant le modèle push, des playbooks YAML et SSH pour automatiser les équipements réseau. _(Module 6, Topic 6.6)_\n\n**Anycast** — Adresse IPv6 unicast assignée à plusieurs interfaces sur des appareils différents ; le paquet est acheminé vers la plus proche. _(Module 1, Topic 1.9)_\n\n**AP (Access Point)** — Point d'accès Wi-Fi convertissant le trafic sans fil en trafic filaire et créant une cellule radio. _(Module 1, Topic 1.1 · Module 2, Topic 2.6)_\n\n**API (Application Programming Interface)** — Interface permettant à un programme d'interagir avec un autre de manière standardisée (REST, NETCONF, etc.). _(Module 6, Topic 6.5)_\n\n**APIPA (Automatic Private IP Addressing)** — Auto-assignation d'une adresse 169.254.x.x quand le DHCP est indisponible (link-local IPv4). _(Module 1, Topic 1.7)_\n\n**ARP (Address Resolution Protocol)** — Protocole IPv4 de résolution d'adresse IP en adresse MAC sur un réseau local. Remplacé par NDP en IPv6. _(Module 1, Topic 1.9 · Module 5, Topic 5.7)_\n\n**ARP Spoofing** — Attaque MitM où l'attaquant associe sa MAC à l'IP de la passerelle via de fausses réponses ARP. _(Module 5, Topic 5.1)_\n\n**Auto-MDIX** — Fonctionnalité détectant automatiquement le type de câble et ajustant les broches, rendant la distinction droit/croisé obsolète. _(Module 1, Topic 1.3)_\n\n**Auto-négociation** — Processus où deux interfaces négocient automatiquement la vitesse et le duplex optimaux du lien. _(Module 1, Topic 1.4)_\n\n## B {#sec-glossaire-b}\n\n**BDR (Backup Designated Router)** — Routeur de secours du DR sur un segment broadcast OSPF ; prend le relais si le DR tombe. _(Module 3, Topic 3.4)_\n\n**BGP (Border Gateway Protocol)** — Protocole de routage inter-domaines (inter-AS) ; AD = 20 (eBGP) / 200 (iBGP). _(Module 3, Topic 3.1)_\n\n**BPDU (Bridge Protocol Data Unit)** — Trame STP échangée entre switches pour élire le root bridge et calculer les rôles de ports. _(Module 2, Topic 2.5)_\n\n**BPDU Guard** — Mécanisme de sécurité désactivant (err-disabled) un port PortFast qui reçoit un BPDU, empêchant un switch non autorisé de rejoindre la topologie. _(Module 2, Topic 2.5)_\n\n**Bridge ID (BID)** — Identifiant unique d'un switch dans STP composé de la priorité (4 bits) + VLAN ID étendu (12 bits) + adresse MAC. _(Module 2, Topic 2.5)_\n\n**Broadcast storm** — Trafic broadcast en boucle infinie dans une topologie redondante sans STP, saturant le réseau en quelques secondes. _(Module 2, Topic 2.5)_\n\n## C {#sec-glossaire-c}\n\n**CAPWAP (Control And Provisioning of Wireless Access Points)** — Protocole tunnel UDP (ports 5246/5247) entre les AP lightweight et le WLC pour le contrôle et les données. _(Module 1, Topic 1.1 · Module 2, Topic 2.6)_\n\n**CDP (Cisco Discovery Protocol)** — Protocole propriétaire Cisco de couche 2 permettant de découvrir les équipements directement connectés (annonces toutes les 60 s). _(Module 1, Topic 1.1 · Module 2, Topic 2.3)_\n\n**CEF (Cisco Express Forwarding)** — Mécanisme de commutation rapide des paquets sur les routeurs Cisco, optimisant le forwarding dans le data plane. _(Module 4, Topic 4.1)_\n\n**Chef** — Outil de gestion de configuration agent-based utilisant le modèle pull, des recipes en Ruby et un Chef Server. _(Module 6, Topic 6.6)_\n\n**CIDR (Classless Inter-Domain Routing)** — Système d'adressage IP sans classes utilisant des préfixes de longueur variable (notation /24, /16, etc.). _(Module 1, Topic 1.6 · Module 3, Topic 3.1)_\n\n**Cisco DNA Center (Catalyst Center)** — Plateforme de gestion réseau centralisée (filaire, sans fil, WAN) avec approche intent-based networking. _(Module 1, Topic 1.1 · Module 6, Topic 6.4)_\n\n**Cisco ISE (Identity Services Engine)** — Plateforme Cisco d'authentification et de politiques de sécurité réseau, serveur AAA supportant TACACS+ et RADIUS. _(Module 1, Topic 1.1 · Module 5, Topic 5.8)_\n\n**Cisco Meraki** — Solution wireless cloud-managed ; AP gérés via un dashboard cloud sans contrôleur physique sur site. _(Module 2, Topic 2.6 · Module 3, Topic 3.6)_\n\n**Class-map** — Objet de configuration IOS définissant les critères de classification du trafic pour les politiques QoS. _(Module 4, Topic 4.7)_\n\n**Conteneur** — Unité d'exécution isolée partageant le noyau de l'OS hôte, démarrage en secondes, taille en mégaoctets (Docker, Podman). _(Module 1, Topic 1.12)_\n\n**Control plane** — Couche décisionnelle d'un équipement réseau (routage, apprentissage MAC, calcul STP), centralisable dans une architecture SDN. _(Module 6, Topic 6.3)_\n\n**CoS (Class of Service)** — Champ de 3 bits dans le tag VLAN 802.1Q (Layer 2) pour le marquage de priorité QoS ; valeurs 0-7. _(Module 2, Topic 2.2 · Module 4, Topic 4.7)_\n\n**CRUD** — Create, Read, Update, Delete : les quatre opérations fondamentales sur les données, mappées aux verbes HTTP dans les APIs REST. _(Module 6, Topic 6.5)_\n\n**CSMA/CD** — Carrier Sense Multiple Access / Collision Detection : méthode d'accès au média partagé Ethernet historique (half-duplex). _(Module 1, Topic 1.3)_\n\n## D {#sec-glossaire-d}\n\n**DAI (Dynamic ARP Inspection)** — Fonctionnalité de switch vérifiant chaque paquet ARP sur les ports untrusted en le comparant à la binding table DHCP snooping. _(Module 5, Topic 5.7)_\n\n**Data plane** — Plan de données (forwarding plane) : couche de transfert effectif des paquets selon les tables construites par le control plane. _(Module 6, Topic 6.3)_\n\n**Default route (route par défaut)** — Route catch-all correspondant à toute destination sans route plus spécifique : 0.0.0.0/0 (IPv4) ou ::/0 (IPv6). _(Module 3, Topic 3.3)_\n\n**DHCP (Dynamic Host Configuration Protocol)** — Protocole client-serveur (UDP 67/68) attribuant automatiquement une configuration IP complète aux clients. Processus en 4 étapes : DORA (Discover, Offer, Request, Acknowledge). _(Module 1, Topic 1.5 · Module 4, Topic 4.3/4.6)_\n\n**DHCP Relay** — Mécanisme convertissant les broadcasts DHCP en unicast pour atteindre un serveur DHCP dans un autre sous-réseau (commande `ip helper-address`). _(Module 4, Topic 4.6)_\n\n**DHCP Snooping** — Fonctionnalité de switch classifiant les ports en trusted/untrusted pour bloquer les serveurs DHCP non autorisés. _(Module 5, Topic 5.7)_\n\n**Diffie-Hellman** — Algorithme d'échange de clés permettant à deux pairs de s'accorder sur une clé partagée via un canal non sécurisé. _(Module 5, Topic 5.5)_\n\n**Distance administrative (AD)** — Entier (0-255) mesurant la confiance du routeur envers la source d'une route ; plus la valeur est basse, plus la source est fiable. _(Module 3, Topic 3.1/3.2)_\n\n**DNS (Domain Name System)** — Service de résolution de noms de domaine en adresses IP, utilisant UDP port 53 (requêtes) et TCP port 53 (transferts de zone). _(Module 1, Topic 1.5 · Module 4, Topic 4.3)_\n\n**DORA** — Les quatre étapes du processus d'attribution DHCP : Discover, Offer, Request, Acknowledge. _(Module 4, Topic 4.3)_\n\n**DR (Designated Router)** — Routeur élu sur un segment broadcast OSPF qui centralise l'échange de LSA, recevant les updates en 224.0.0.6. _(Module 3, Topic 3.4)_\n\n**DSCP (Differentiated Services Code Point)** — Champ de 6 bits dans l'en-tête IP (Layer 3) marquant la classe de service du paquet ; valeurs 0-63, préservé de bout en bout. _(Module 4, Topic 4.7)_\n\n**DTP (Dynamic Trunking Protocol)** — Protocole propriétaire Cisco négociant automatiquement le mode trunk/access entre deux ports de switch. _(Module 2, Topic 2.2)_\n\n**Dual-stack** — Configuration où une interface supporte simultanément IPv4 et IPv6. _(Module 1, Topic 1.8)_\n\n**Duplex mismatch** — Problème où un côté du lien est en full-duplex et l'autre en half-duplex, causant des late collisions et des CRC errors. _(Module 1, Topic 1.4)_\n\n## E {#sec-glossaire-e}\n\n**ECMP (Equal-Cost Multi-Path)** — Technique de routage répartissant le trafic sur plusieurs chemins de coût égal vers la même destination. _(Module 1, Topic 1.2 · Module 3, Topic 3.2)_\n\n**EF (Expedited Forwarding)** — Classe DSCP (valeur décimale 46) pour la voix, garantissant priorité maximale et latence minimale. _(Module 4, Topic 4.7)_\n\n**EIGRP (Enhanced Interior Gateway Routing Protocol)** — Protocole de routage hybride Cisco ; AD = 90 (interne) / 170 (externe), métrique composite (bande passante + délai). _(Module 3, Topic 3.1)_\n\n**Encapsulation** — Processus d'ajout d'en-têtes de protocole à chaque couche du modèle OSI lors de la transmission de données. _(Module 1, Topic 1.4)_\n\n**err-disabled** — État d'un port de switch désactivé automatiquement par une fonctionnalité de sécurité (BPDU Guard, port security, etc.). _(Module 2, Topic 2.5 · Module 5, Topic 5.7)_\n\n**ESP (Encapsulating Security Payload)** — Protocole IPsec (IP Protocol 50) fournissant chiffrement + intégrité + authentification ; le plus utilisé. _(Module 5, Topic 5.5)_\n\n**EtherChannel** — Technologie regroupant 2 à 8 liens physiques en un seul lien logique pour augmenter la bande passante et la redondance. _(Module 2, Topic 2.4)_\n\n**EUI-64 (Modified)** — Méthode de génération automatique de l'Interface ID IPv6 (64 bits) à partir de l'adresse MAC (48 bits) en insérant FF:FE et inversant le 7e bit. _(Module 1, Topic 1.9)_\n\n## F {#sec-glossaire-f}\n\n**Fabric** — Combinaison de l'overlay et de l'underlay orchestrée par le contrôleur SDN, désignant le réseau SDN complet. _(Module 6, Topic 6.3)_\n\n**FHRP (First Hop Redundancy Protocol)** — Famille de protocoles (HSRP, VRRP, GLBP) créant une IP virtuelle partagée entre routeurs pour la redondance de passerelle. _(Module 3, Topic 3.5)_\n\n**Fibre monomode (SMF)** — Fibre optique à cœur fin (9 µm), source laser, portée jusqu'à 80+ km. _(Module 1, Topic 1.3)_\n\n**Fibre multimode (MMF)** — Fibre optique à cœur large (50/62,5 µm), source LED/VCSEL, portée jusqu'à 550 m en 10G. _(Module 1, Topic 1.3)_\n\n**FlexConnect** — Mode AP hybride géré par le WLC mais capable de commuter le trafic localement ; survie en cas de perte du WLC. _(Module 2, Topic 2.6)_\n\n**Floating static route** — Route statique avec une AD volontairement augmentée pour servir de route de secours, invisible tant qu'une route dynamique préférable existe. _(Module 3, Topic 3.3)_\n\n**Flooding** — Envoi d'une trame sur tous les ports du même VLAN sauf le port source, pour les unknown unicast, broadcast et multicast. _(Module 1, Topic 1.13)_\n\n**FTP (File Transfer Protocol)** — Protocole de transfert de fichiers complet (TCP ports 20/21) avec authentification, mais credentials transmis en clair. _(Module 1, Topic 1.5 · Module 4, Topic 4.9)_\n\n**Full-duplex** — Mode de communication permettant l'émission et la réception simultanées sur un lien Ethernet. _(Module 1, Topic 1.3)_\n\n## G {#sec-glossaire-g}\n\n**Gateway of last resort** — Route par défaut active du routeur (0.0.0.0/0) ; si non configurée, les paquets sans route spécifique sont jetés. _(Module 3, Topic 3.1)_\n\n**GLBP (Gateway Load Balancing Protocol)** — Protocole FHRP propriétaire Cisco avec load balancing natif via MAC virtuelles multiples. _(Module 3, Topic 3.5)_\n\n**GRE (Generic Routing Encapsulation)** — Protocole de tunneling encapsulant des paquets multicast/non-IP ; souvent combiné avec IPsec pour les VPN site-to-site. _(Module 5, Topic 5.5 · Module 6, Topic 6.3)_\n\n**GUA (Global Unicast Address)** — Adresse IPv6 routable sur Internet (préfixe 2000::/3), équivalent des adresses publiques IPv4. _(Module 1, Topic 1.9)_\n\n## H {#sec-glossaire-h}\n\n**HSRP (Hot Standby Router Protocol)** — Protocole FHRP propriétaire Cisco ; rôles Active/Standby/Listen, préemption désactivée par défaut. _(Module 3, Topic 3.5)_\n\n**HTTP / HTTPS** — Protocoles web non chiffré (TCP 80) / chiffré TLS (TCP 443) ; HTTPS est aussi utilisé comme transport pour les APIs REST. _(Module 1, Topic 1.5 · Module 6, Topic 6.5)_\n\n**Hyperviseur** — Logiciel créant et gérant des machines virtuelles. Type 1 (bare-metal : ESXi, Hyper-V, KVM) ou Type 2 (hosted : VMware Workstation, VirtualBox). _(Module 1, Topic 1.12)_\n\n## I {#sec-glossaire-i}\n\n**IA générative** — Système d'intelligence artificielle capable de produire du contenu nouveau (configurations, analyses) à partir de prompts en langage naturel. _(Module 1, Topic 1.14)_\n\n**ICMP (Internet Control Message Protocol)** — Protocole de couche 3 utilisé pour les messages de diagnostic réseau (ping, traceroute). _(Module 1, Topic 1.10 · Module 3, Topic 3.3)_\n\n**Idempotence** — Propriété garantissant qu'exécuter une opération plusieurs fois produit toujours le même résultat, sans effet de bord supplémentaire. _(Module 6, Topic 6.6)_\n\n**IKE (Internet Key Exchange)** — Protocole de négociation IPsec en deux phases pour l'authentification et l'échange de clés sécurisés. _(Module 5, Topic 5.5)_\n\n**Intent-Based Networking (IBN)** — Gestion réseau automatisée où l'administrateur exprime une intention et le système la traduit en configuration technique. _(Module 1, Topic 1.1 · Module 6, Topic 6.4)_\n\n**IPS (Intrusion Prevention System)** — Système analysant le trafic en temps réel pour détecter et bloquer les attaques réseau connues. _(Module 1, Topic 1.1 · Module 5, Topic 5.1)_\n\n**IPsec** — Suite de protocoles de sécurité pour le chiffrement et l'authentification des paquets IP, utilisée dans les VPN site-to-site et remote access. _(Module 1, Topic 1.2 · Module 5, Topic 5.5)_\n\n**IPv4** — Protocole d'adressage réseau utilisant des adresses de 32 bits en notation décimale pointée (ex : 192.168.1.10). _(Module 1, Topic 1.6)_\n\n**IPv6** — Protocole d'adressage réseau utilisant des adresses de 128 bits en notation hexadécimale, remplaçant IPv4. _(Module 1, Topic 1.8)_\n\n## J {#sec-glossaire-j}\n\n**JSON (JavaScript Object Notation)** — Format de données léger et lisible, standard de facto pour les APIs REST et l'automatisation réseau. _(Module 6, Topic 6.7)_\n\n## K {#sec-glossaire-k}\n\n**Kubernetes** — Système d'orchestration de conteneurs gérant le déploiement, le scaling et la gestion de conteneurs à grande échelle. _(Module 1, Topic 1.12)_\n\n## L {#sec-glossaire-l}\n\n**LACP (Link Aggregation Control Protocol)** — Protocole standard IEEE 802.3ad de négociation d'EtherChannel avec modes active et passive. _(Module 2, Topic 2.4)_\n\n**Link-Local (FE80::/10)** — Adresse IPv6 valide uniquement sur le lien local, générée automatiquement, utilisée par les protocoles de routage. _(Module 1, Topic 1.9)_\n\n**Link-state** — Type de protocole de routage où chaque routeur possède une carte complète de la topologie et calcule ses routes indépendamment (OSPF, IS-IS). _(Module 3, Topic 3.4)_\n\n**LLDP (Link Layer Discovery Protocol)** — Protocole standard IEEE 802.1AB de découverte Layer 2, multi-vendeur, à activer manuellement sur les équipements Cisco. _(Module 2, Topic 2.3)_\n\n**Longest prefix match** — Règle fondamentale du routage IP : le routeur sélectionne toujours la route dont le masque est le plus long (le plus spécifique). _(Module 1, Topic 1.6 · Module 3, Topic 3.2)_\n\n**LSA (Link-State Advertisement)** — Unité d'information OSPF décrivant un lien ou un réseau, stockée dans la LSDB et échangée entre routeurs. _(Module 3, Topic 3.4)_\n\n**LSDB (Link-State Database)** — Base de données topologique OSPF contenant tous les LSA ; identique sur tous les routeurs d'une même area. _(Module 3, Topic 3.4)_\n\n## M {#sec-glossaire-m}\n\n**MAC (Media Access Control)** — Adresse physique de 48 bits identifiant de manière unique une interface réseau sur un segment L2. _(Module 1, Topic 1.1/1.13)_\n\n**MAC address table (CAM table)** — Table d'un switch associant les adresses MAC aux ports et VLANs, avec un aging time par défaut de 300 secondes. _(Module 1, Topic 1.13)_\n\n**Machine Learning (ML)** — Approche d'intelligence artificielle où les systèmes apprennent à partir de données pour détecter des anomalies et des menaces réseau. _(Module 5, Topic 5.11)_\n\n**MFA (Multi-Factor Authentication)** — Authentification multifacteur combinant au moins deux catégories : connaissance, possession, inhérence. _(Module 5, Topic 5.4)_\n\n**MIB (Management Information Base)** — Base de données hiérarchique en arbre contenant les variables supervisables d'un équipement SNMP (OIDs). _(Module 4, Topic 4.4)_\n\n**Modèle OSI** — Modèle de référence en 7 couches (physique, liaison, réseau, transport, session, présentation, application) pour la communication réseau. _(Module 1, Topic 1.1)_\n\n**MPLS (Multiprotocol Label Switching)** — Technologie WAN opérateur utilisant des labels pour acheminer les paquets avec des garanties de SLA. _(Module 1, Topic 1.2)_\n\n**MTU (Maximum Transmission Unit)** — Taille maximale d'un paquet transmissible sur un lien sans fragmentation (1500 octets par défaut en Ethernet). _(Module 1, Topic 1.4 · Module 3, Topic 3.4)_\n\n**Multicast** — Mode de transmission envoyant des paquets à un groupe spécifique d'adresses (ex : 224.0.0.5 pour OSPF, FF02::1 en IPv6). _(Module 1, Topic 1.9 · Module 3, Topic 3.4)_\n\n## N {#sec-glossaire-n}\n\n**NAT (Network Address Translation)** — Technique remplaçant les adresses IP privées par une adresse publique pour l'accès à Internet. _(Module 1, Topic 1.7 · Module 4, Topic 4.1)_\n\n**NBAR (Network-Based Application Recognition)** — Technologie Cisco de reconnaissance d'application au niveau Layer 7 pour la classification QoS. _(Module 4, Topic 4.7)_\n\n**NDP (Neighbor Discovery Protocol)** — Protocole IPv6 remplaçant ARP, assurant la découverte des voisins, l'auto-configuration et la détection de duplication (DAD). _(Module 1, Topic 1.9)_\n\n**NETCONF** — Protocole southbound API basé sur XML et SSH, utilisé pour configurer les équipements réseau de manière programmatique. _(Module 6, Topic 6.3)_\n\n**NetFlow** — Technologie Cisco exportant les métadonnées de flux réseau (source, destination, ports, octets) vers un collecteur pour analyse. _(Module 5, Topic 5.11)_\n\n**NGFW (Next-Generation Firewall)** — Pare-feu nouvelle génération inspectant le trafic jusqu'à la couche 7, avec détection de malwares et politiques basées sur l'identité. _(Module 1, Topic 1.1)_\n\n**Northbound API** — Interface entre les applications et le contrôleur SDN (vers le haut), typiquement REST/HTTP. _(Module 6, Topic 6.3)_\n\n**NTP (Network Time Protocol)** — Protocole de synchronisation horaire utilisant UDP port 123 avec une hiérarchie de stratum (0 = horloge atomique). _(Module 1, Topic 1.5 · Module 4, Topic 4.2)_\n\n## O {#sec-glossaire-o}\n\n**OID (Object Identifier)** — Identifiant numérique hiérarchique unique d'une variable dans la MIB SNMP (ex : 1.3.6.1.2.1.1.5 pour sysName). _(Module 4, Topic 4.4)_\n\n**OpenFlow** — Protocole southbound API originel du SDN, permettant au contrôleur de programmer directement les tables de forwarding des équipements. _(Module 6, Topic 6.3)_\n\n**OSPF (Open Shortest Path First)** — Protocole de routage link-state utilisant l'algorithme SPF (Dijkstra) ; AD = 110, métrique basée sur le coût (bande passante). _(Module 3, Topic 3.4)_\n\n**OSPFv3** — Version d'OSPF pour IPv6 (RFC 5340), utilisant les adresses link-local comme adresses de next-hop. _(Module 1, Topic 1.9 · Module 3, Topic 3.4)_\n\n**Overlay** — Réseau virtuel construit par-dessus le réseau physique via des tunnels (VXLAN, GRE, IPsec). _(Module 6, Topic 6.3)_\n\n**OWE (Opportunistic Wireless Encryption)** — Chiffrement automatique des réseaux Wi-Fi ouverts (sans mot de passe) introduit avec WPA3. _(Module 5, Topic 5.9)_\n\n## P {#sec-glossaire-p}\n\n**PAgP (Port Aggregation Protocol)** — Protocole propriétaire Cisco de négociation d'EtherChannel avec modes desirable et auto. _(Module 2, Topic 2.4)_\n\n**passive-interface** — Commande OSPF empêchant l'envoi de Hello sur une interface tout en annonçant son réseau aux voisins. _(Module 3, Topic 3.4)_\n\n**PAT (Port Address Translation)** — NAT overload : tous les hôtes internes partagent une seule adresse publique, distingués par numéros de port source. _(Module 4, Topic 4.1)_\n\n**PHB (Per-Hop Behavior)** — Comportement de traitement QoS appliqué indépendamment par chaque équipement réseau à chaque saut. _(Module 4, Topic 4.7)_\n\n**PKI (Public Key Infrastructure)** — Infrastructure à clés publiques gérant les certificats numériques (émission, révocation, renouvellement). _(Module 5, Topic 5.4)_\n\n**PMF (Protected Management Frames)** — Protection des trames de gestion Wi-Fi ; optionnel en WPA2, obligatoire en WPA3. _(Module 5, Topic 5.9)_\n\n**PnP (Plug and Play)** — Mécanisme Cisco d'onboarding automatique des équipements réseau via DNA Center, sans configuration manuelle préalable. _(Module 6, Topic 6.4)_\n\n**PoE (Power over Ethernet)** — Technologie permettant d'alimenter un appareil réseau via le câble Ethernet. Standards : 802.3af (15,4 W), 802.3at/PoE+ (30 W), 802.3bt (60-90 W). _(Module 1, Topic 1.1 · Module 2, Topic 2.7)_\n\n**Policy-map** — Objet de configuration IOS définissant les actions QoS (marquage, queuing, policing) à appliquer aux classes de trafic. _(Module 4, Topic 4.7)_\n\n**Port-Channel** — Interface logique représentant un EtherChannel ; STP la traite comme un port unique. _(Module 2, Topic 2.4)_\n\n**PortFast** — Fonctionnalité STP permettant à un port d'accès de passer immédiatement en Forwarding sans attendre la convergence. _(Module 2, Topic 2.5)_\n\n**Port Security** — Fonctionnalité de switch limitant le nombre d'adresses MAC autorisées par port pour prévenir le MAC flooding. _(Module 1, Topic 1.13 · Module 5, Topic 5.7)_\n\n**PSK (Pre-Shared Key)** — Mode d'authentification avec un mot de passe partagé entre tous les utilisateurs (Wi-Fi Personal, IPsec). _(Module 1, Topic 1.11 · Module 5, Topic 5.5)_\n\n**Puppet** — Outil de gestion de configuration agent-based utilisant le modèle pull, des manifests en DSL propriétaire et un Puppet Master. _(Module 6, Topic 6.6)_\n\n## Q {#sec-glossaire-q}\n\n**QoS (Quality of Service)** — Ensemble de mécanismes priorisant certains types de trafic réseau (classification, marquage, queuing, policing, shaping). _(Module 4, Topic 4.7)_\n\n## R {#sec-glossaire-r}\n\n**RADIUS (Remote Authentication Dial-In User Service)** — Protocole AAA standard (UDP 1812/1813) ne chiffrant que le mot de passe, combinant Auth+Authz ; utilisé pour Wi-Fi/VPN/802.1X. _(Module 2, Topic 2.8 · Module 5, Topic 5.8)_\n\n**Rapid PVST+** — Version améliorée de STP par défaut sur les switches Cisco : convergence rapide (1-2 s) et un arbre STP distinct par VLAN. _(Module 2, Topic 2.5)_\n\n**REST (Representational State Transfer)** — Style d'architecture pour les services web utilisant HTTP comme protocole de communication (stateless, URI, verbes HTTP). _(Module 6, Topic 6.5)_\n\n**RESTCONF** — API RESTful combinant les principes REST (HTTP) avec les modèles de données YANG de NETCONF. _(Module 6, Topic 6.3)_\n\n**RFC 1918** — Standard définissant les trois plages d'adresses IPv4 privées non routables (10.0.0.0/8, 172.16.0.0/12, 192.168.0.0/16). _(Module 1, Topic 1.7)_\n\n**RIP (Routing Information Protocol)** — Protocole de routage distance-vector ; AD = 120, métrique = hop count (maximum 15 sauts). _(Module 3, Topic 3.1)_\n\n**Root bridge** — Switch élu comme racine de l'arbre STP, ayant le Bridge ID le plus bas ; tous ses ports sont Designated. _(Module 2, Topic 2.5)_\n\n**Root Port (RP)** — Port sur un switch non-root ayant le meilleur chemin (coût le plus bas) vers le root bridge ; un seul par switch. _(Module 2, Topic 2.5)_\n\n**Router ID (RID)** — Identifiant unique de 32 bits au format IPv4 pour chaque routeur OSPF. Priorité : commande `router-id` > IP loopback la plus haute > IP physique la plus haute. _(Module 3, Topic 3.4)_\n\n**Router-on-a-stick** — Méthode de routage inter-VLAN utilisant un seul lien trunk entre le switch et le routeur, avec des sous-interfaces dot1Q. _(Module 2, Topic 2.1 · Module 3, Topic 3.4)_\n\n**RSA** — Algorithme de chiffrement asymétrique utilisé pour générer les clés SSH (minimum 2048 bits recommandé). _(Module 2, Topic 2.8 · Module 5, Topic 5.5)_\n\n## S {#sec-glossaire-s}\n\n**SAE (Simultaneous Authentication of Equals)** — Mécanisme d'authentification WPA3 remplaçant PSK, résistant aux attaques par dictionnaire offline. _(Module 1, Topic 1.11 · Module 5, Topic 5.9)_\n\n**SD-Access** — Solution SDN Cisco de campus utilisant DNA Center, LISP, VXLAN et TrustSec pour la fabric. _(Module 6, Topic 6.3)_\n\n**SD-WAN (Software-Defined WAN)** — Architecture SDN pour les réseaux étendus, utilisant vManage comme contrôleur et IPsec pour l'overlay. _(Module 1, Topic 1.2 · Module 6, Topic 6.3)_\n\n**SDN (Software-Defined Networking)** — Architecture réseau où le control plane est centralisé sur un contrôleur, séparant les décisions de l'acheminement du trafic. _(Module 6, Topic 6.3)_\n\n**Shaping** — Mécanisme QoS retardant (buffer) les paquets pour lisser le débit de sortie ; applicable uniquement en sortie. _(Module 4, Topic 4.7)_\n\n**show ip interface brief** — Commande Cisco affichant un résumé de toutes les interfaces avec leur adresse IP et leur statut (up/down). _(Module 1, Topic 1.6)_\n\n**show ip ospf neighbor** — Commande CLI affichant les voisins OSPF avec leur Router ID, priorité, état, dead time, adresse et interface. _(Module 3, Topic 3.4)_\n\n**show ip route** — Commande Cisco affichant la table de routage IPv4 complète avec codes, préfixes, masques, next-hops et métriques. _(Module 3, Topic 3.1)_\n\n**show mac address-table** — Commande Cisco affichant toute la table d'adresses MAC du switch avec les VLANs et ports associés. _(Module 1, Topic 1.13)_\n\n**show spanning-tree** — Commande affichant l'état STP pour un VLAN : root bridge, bridge local, rôles et états de chaque port. _(Module 2, Topic 2.5)_\n\n**show vlan brief** — Commande de vérification affichant la liste des VLANs, leur nom, statut et ports associés. _(Module 2, Topic 2.1)_\n\n**SLAAC (Stateless Address Autoconfiguration)** — Mécanisme IPv6 d'auto-configuration des adresses sans serveur DHCP, basé sur le préfixe annoncé par le routeur. _(Module 1, Topic 1.8)_\n\n**SNMP (Simple Network Management Protocol)** — Protocole de supervision réseau (UDP 161/162). Versions : v1/v2c (community strings en clair), v3 (authentification + chiffrement). _(Module 1, Topic 1.5 · Module 4, Topic 4.4)_\n\n**SOHO (Small Office / Home Office)** — Architecture réseau simplifiée avec un seul appareil multifonction (routeur/switch/Wi-Fi/NAT/DHCP). _(Module 1, Topic 1.2)_\n\n**Southbound API** — Interface entre le contrôleur SDN et les équipements réseau (vers le bas), typiquement NETCONF, RESTCONF, OpenFlow. _(Module 6, Topic 6.3)_\n\n**Spine-Leaf** — Architecture de datacenter garantissant un nombre de hops constant (2) entre serveurs, optimisée pour le trafic est-ouest. _(Module 1, Topic 1.2)_\n\n**SPF (Shortest Path First / Dijkstra)** — Algorithme utilisé par OSPF pour calculer le chemin le plus court vers chaque destination dans la topologie. _(Module 3, Topic 3.4)_\n\n**SSH (Secure Shell)** — Protocole d'accès distant sécurisé (chiffré) utilisant TCP port 22, remplaçant Telnet. SSHv2 est le standard. _(Module 1, Topic 1.5 · Module 4, Topic 4.8)_\n\n**SSID (Service Set Identifier)** — Nom du réseau Wi-Fi visible par les clients ; un AP peut diffuser plusieurs SSID. _(Module 1, Topic 1.11 · Module 2, Topic 2.9)_\n\n**STP (Spanning Tree Protocol)** — Protocole de couche 2 empêchant les boucles en désactivant logiquement certains liens redondants. _(Module 1, Topic 1.13 · Module 2, Topic 2.5)_\n\n**Stratum (NTP)** — Niveau hiérarchique NTP indiquant la distance à la source de référence ; 0 = horloge atomique, 16 = non synchronisé. _(Module 4, Topic 4.2)_\n\n**Subnetting** — Technique de découpage d'un réseau en sous-réseaux en empruntant des bits de la partie hôte. _(Module 1, Topic 1.6)_\n\n**SVI (Switch Virtual Interface)** — Interface virtuelle sur un switch L3 associée à un VLAN, servant de passerelle par défaut pour ce VLAN. _(Module 1, Topic 1.1 · Module 2, Topic 2.1)_\n\n**Syslog** — Standard de journalisation réseau (RFC 5424, UDP 514). Niveaux de sévérité de 0 (Emergency) à 7 (Debugging). _(Module 1, Topic 1.5 · Module 4, Topic 4.5)_\n\n## T {#sec-glossaire-t}\n\n**TACACS+** — Protocole AAA propriétaire Cisco (TCP 49) chiffrant le paquet entier, avec séparation Auth/Authz/Acct et autorisation par commande. _(Module 2, Topic 2.8 · Module 5, Topic 5.8)_\n\n**TCP (Transmission Control Protocol)** — Protocole de transport fiable orienté connexion avec accusé de réception, numéros de séquence et contrôle de flux (couche 4). _(Module 1, Topic 1.5)_\n\n**TFTP (Trivial File Transfer Protocol)** — Protocole de transfert de fichiers minimaliste (UDP port 69) sans authentification ; utilisé pour les mises à jour IOS et sauvegardes. _(Module 1, Topic 1.5 · Module 4, Topic 4.9)_\n\n**Three-tier** — Architecture réseau à trois couches (accès, distribution, cœur) pour les grands campus (>500 utilisateurs). _(Module 1, Topic 1.2)_\n\n**Three-way handshake** — Processus d'établissement de connexion TCP en trois étapes : SYN, SYN-ACK, ACK. _(Module 1, Topic 1.5)_\n\n**TLS (Transport Layer Security)** — Protocole de chiffrement assurant la confidentialité des communications HTTPS, SSH et VPN SSL. _(Module 2, Topic 2.8 · Module 5, Topic 5.11)_\n\n**Trunk (port trunk)** — Port de switch transportant les trames de plusieurs VLANs sur un seul lien physique, grâce au tagging 802.1Q. _(Module 2, Topic 2.2)_\n\n**Two-tier (Collapsed Core)** — Architecture réseau à deux niveaux combinant distribution et cœur, adaptée aux campus de petite/moyenne taille. _(Module 1, Topic 1.2)_\n\n## U {#sec-glossaire-u}\n\n**UDP (User Datagram Protocol)** — Protocole de transport sans connexion, rapide et à faible overhead (8 octets d'en-tête), sans fiabilité intégrée (couche 4). _(Module 1, Topic 1.5)_\n\n**ULA (Unique Local Address)** — Adresse IPv6 privée non routable (préfixe FC00::/7), équivalent de RFC 1918 en IPv4. _(Module 1, Topic 1.9)_\n\n**Underlay** — Réseau physique sous-jacent (câbles, switches, routeurs) fournissant la connectivité IP de base pour le transport overlay. _(Module 6, Topic 6.3)_\n\n## V {#sec-glossaire-v}\n\n**VLAN (Virtual LAN)** — Réseau local virtuel segmentant logiquement un switch en plusieurs domaines de broadcast indépendants. _(Module 1, Topic 1.13 · Module 2, Topic 2.1)_\n\n**VLAN natif (native VLAN)** — VLAN dont les trames traversent le trunk sans tag 802.1Q ; par défaut VLAN 1. Un mismatch entre extrémités cause des erreurs. _(Module 2, Topic 2.2)_\n\n**VLSM (Variable-Length Subnet Masking)** — Technique de subnetting utilisant des masques de longueurs différentes pour optimiser l'espace d'adressage. _(Module 1, Topic 1.6 · Module 3, Topic 3.4)_\n\n**VPN (Virtual Private Network)** — Tunnel chiffré établi sur un réseau public pour sécuriser les communications. Types : site-to-site (IPsec) et remote access (SSL/AnyConnect). _(Module 1, Topic 1.2 · Module 5, Topic 5.5)_\n\n**VRF (Virtual Routing and Forwarding)** — Virtualisation de la table de routage permettant à un seul routeur de maintenir plusieurs tables indépendantes et isolées. _(Module 1, Topic 1.12 · Module 6, Topic 6.3)_\n\n**VRRP (Virtual Router Redundancy Protocol)** — Protocole FHRP standard IETF (RFC 5798) ; rôles Master/Backup, préemption activée par défaut. _(Module 3, Topic 3.5)_\n\n**VTY (Virtual Terminal Line)** — Ligne virtuelle sur un équipement Cisco permettant les connexions distantes SSH/Telnet ; typiquement 0-15. _(Module 2, Topic 2.8 · Module 4, Topic 4.8)_\n\n**VXLAN (Virtual Extensible LAN)** — Technologie d'encapsulation overlay étendant les VLANs à travers un réseau IP (underlay), utilisée par SD-Access. _(Module 6, Topic 6.3)_\n\n## W {#sec-glossaire-w}\n\n**WAN (Wide Area Network)** — Réseau étendu connectant des sites géographiquement dispersés via MPLS, VPN, SD-WAN ou Metro Ethernet. _(Module 1, Topic 1.2)_\n\n**Wildcard mask** — Masque inversé du masque de sous-réseau, utilisé dans les ACL et les configurations OSPF (ex : 0.0.0.255 = /24). _(Module 3, Topic 3.4 · Module 5, Topic 5.6)_\n\n**WLC (Wireless LAN Controller)** — Contrôleur centralisant la gestion de tous les AP lightweight (SSID, sécurité, canaux, puissance, roaming). _(Module 1, Topic 1.1 · Module 2, Topic 2.6)_\n\n**WPA2** — Standard de sécurité Wi-Fi utilisant AES-CCMP 128 bits. Modes : Personal (PSK) et Enterprise (802.1X/RADIUS). _(Module 1, Topic 1.11 · Module 5, Topic 5.9)_\n\n**WPA3** — Dernier standard de sécurité Wi-Fi utilisant AES-GCMP et SAE, avec PMF obligatoire et OWE pour les réseaux ouverts. _(Module 1, Topic 1.11 · Module 5, Topic 5.9)_\n\n**WRED (Weighted Random Early Detection)** — Mécanisme d'évitement de congestion rejetant aléatoirement des paquets avant saturation de file, basé sur la probabilité de drop. _(Module 4, Topic 4.7)_\n\n## X-Z {#sec-glossaire-xz}\n\n**XML (eXtensible Markup Language)** — Format de données structuré avec balises, utilisé historiquement par SOAP et NETCONF pour la configuration réseau. _(Module 6, Topic 6.7)_\n\n**YAML** — Format de sérialisation de données lisible par l'humain, utilisé par les playbooks Ansible pour définir les tâches d'automatisation. _(Module 6, Topic 6.6)_\n\n**Zero-Touch Provisioning (ZTP)** — Mécanisme de déploiement automatique où un équipement neuf se configure en contactant le cloud, sans intervention humaine. _(Module 2, Topic 2.8 · Module 3, Topic 3.6)_\n","srcMarkdownNoYaml":"\n\n## A {#sec-glossaire-a}\n\n**AAA (Authentication, Authorization, Accounting)** — Cadre centralisant l'authentification (qui êtes-vous ?), l'autorisation (que pouvez-vous faire ?) et la traçabilité (qu'avez-vous fait ?) des accès réseau. _(Module 2, Topic 2.8 · Module 5, Topic 5.8)_\n\n**ACE (Access Control Entry)** — Règle individuelle dans une ACL, spécifiant une action `permit` ou `deny` pour un trafic correspondant à des critères donnés. _(Module 5, Topic 5.6)_\n\n**ACI (Application Centric Infrastructure)** — Solution SDN Cisco pour datacenter avec le contrôleur APIC et l'overlay VXLAN. _(Module 6, Topic 6.3)_\n\n**ACL (Access Control List)** — Liste ordonnée de règles filtrant le trafic réseau sur la base d'adresses IP, de ports et de protocoles. _(Module 5, Topic 5.6 · Module 4, Topic 4.1)_\n\n**AES-CCMP** — Algorithme de chiffrement utilisé par WPA2 (Advanced Encryption Standard – Counter Mode with CBC-MAC Protocol, 128 bits). _(Module 1, Topic 1.11 · Module 5, Topic 5.9)_\n\n**AES-GCMP** — Algorithme de chiffrement utilisé par WPA3 (AES – Galois/Counter Mode Protocol, 128/256 bits). _(Module 5, Topic 5.9)_\n\n**AH (Authentication Header)** — Protocole IPsec (IP Protocol 51) fournissant l'intégrité et l'authentification des paquets, sans chiffrement. _(Module 5, Topic 5.5)_\n\n**Ansible** — Outil de gestion de configuration agentless utilisant le modèle push, des playbooks YAML et SSH pour automatiser les équipements réseau. _(Module 6, Topic 6.6)_\n\n**Anycast** — Adresse IPv6 unicast assignée à plusieurs interfaces sur des appareils différents ; le paquet est acheminé vers la plus proche. _(Module 1, Topic 1.9)_\n\n**AP (Access Point)** — Point d'accès Wi-Fi convertissant le trafic sans fil en trafic filaire et créant une cellule radio. _(Module 1, Topic 1.1 · Module 2, Topic 2.6)_\n\n**API (Application Programming Interface)** — Interface permettant à un programme d'interagir avec un autre de manière standardisée (REST, NETCONF, etc.). _(Module 6, Topic 6.5)_\n\n**APIPA (Automatic Private IP Addressing)** — Auto-assignation d'une adresse 169.254.x.x quand le DHCP est indisponible (link-local IPv4). _(Module 1, Topic 1.7)_\n\n**ARP (Address Resolution Protocol)** — Protocole IPv4 de résolution d'adresse IP en adresse MAC sur un réseau local. Remplacé par NDP en IPv6. _(Module 1, Topic 1.9 · Module 5, Topic 5.7)_\n\n**ARP Spoofing** — Attaque MitM où l'attaquant associe sa MAC à l'IP de la passerelle via de fausses réponses ARP. _(Module 5, Topic 5.1)_\n\n**Auto-MDIX** — Fonctionnalité détectant automatiquement le type de câble et ajustant les broches, rendant la distinction droit/croisé obsolète. _(Module 1, Topic 1.3)_\n\n**Auto-négociation** — Processus où deux interfaces négocient automatiquement la vitesse et le duplex optimaux du lien. _(Module 1, Topic 1.4)_\n\n## B {#sec-glossaire-b}\n\n**BDR (Backup Designated Router)** — Routeur de secours du DR sur un segment broadcast OSPF ; prend le relais si le DR tombe. _(Module 3, Topic 3.4)_\n\n**BGP (Border Gateway Protocol)** — Protocole de routage inter-domaines (inter-AS) ; AD = 20 (eBGP) / 200 (iBGP). _(Module 3, Topic 3.1)_\n\n**BPDU (Bridge Protocol Data Unit)** — Trame STP échangée entre switches pour élire le root bridge et calculer les rôles de ports. _(Module 2, Topic 2.5)_\n\n**BPDU Guard** — Mécanisme de sécurité désactivant (err-disabled) un port PortFast qui reçoit un BPDU, empêchant un switch non autorisé de rejoindre la topologie. _(Module 2, Topic 2.5)_\n\n**Bridge ID (BID)** — Identifiant unique d'un switch dans STP composé de la priorité (4 bits) + VLAN ID étendu (12 bits) + adresse MAC. _(Module 2, Topic 2.5)_\n\n**Broadcast storm** — Trafic broadcast en boucle infinie dans une topologie redondante sans STP, saturant le réseau en quelques secondes. _(Module 2, Topic 2.5)_\n\n## C {#sec-glossaire-c}\n\n**CAPWAP (Control And Provisioning of Wireless Access Points)** — Protocole tunnel UDP (ports 5246/5247) entre les AP lightweight et le WLC pour le contrôle et les données. _(Module 1, Topic 1.1 · Module 2, Topic 2.6)_\n\n**CDP (Cisco Discovery Protocol)** — Protocole propriétaire Cisco de couche 2 permettant de découvrir les équipements directement connectés (annonces toutes les 60 s). _(Module 1, Topic 1.1 · Module 2, Topic 2.3)_\n\n**CEF (Cisco Express Forwarding)** — Mécanisme de commutation rapide des paquets sur les routeurs Cisco, optimisant le forwarding dans le data plane. _(Module 4, Topic 4.1)_\n\n**Chef** — Outil de gestion de configuration agent-based utilisant le modèle pull, des recipes en Ruby et un Chef Server. _(Module 6, Topic 6.6)_\n\n**CIDR (Classless Inter-Domain Routing)** — Système d'adressage IP sans classes utilisant des préfixes de longueur variable (notation /24, /16, etc.). _(Module 1, Topic 1.6 · Module 3, Topic 3.1)_\n\n**Cisco DNA Center (Catalyst Center)** — Plateforme de gestion réseau centralisée (filaire, sans fil, WAN) avec approche intent-based networking. _(Module 1, Topic 1.1 · Module 6, Topic 6.4)_\n\n**Cisco ISE (Identity Services Engine)** — Plateforme Cisco d'authentification et de politiques de sécurité réseau, serveur AAA supportant TACACS+ et RADIUS. _(Module 1, Topic 1.1 · Module 5, Topic 5.8)_\n\n**Cisco Meraki** — Solution wireless cloud-managed ; AP gérés via un dashboard cloud sans contrôleur physique sur site. _(Module 2, Topic 2.6 · Module 3, Topic 3.6)_\n\n**Class-map** — Objet de configuration IOS définissant les critères de classification du trafic pour les politiques QoS. _(Module 4, Topic 4.7)_\n\n**Conteneur** — Unité d'exécution isolée partageant le noyau de l'OS hôte, démarrage en secondes, taille en mégaoctets (Docker, Podman). _(Module 1, Topic 1.12)_\n\n**Control plane** — Couche décisionnelle d'un équipement réseau (routage, apprentissage MAC, calcul STP), centralisable dans une architecture SDN. _(Module 6, Topic 6.3)_\n\n**CoS (Class of Service)** — Champ de 3 bits dans le tag VLAN 802.1Q (Layer 2) pour le marquage de priorité QoS ; valeurs 0-7. _(Module 2, Topic 2.2 · Module 4, Topic 4.7)_\n\n**CRUD** — Create, Read, Update, Delete : les quatre opérations fondamentales sur les données, mappées aux verbes HTTP dans les APIs REST. _(Module 6, Topic 6.5)_\n\n**CSMA/CD** — Carrier Sense Multiple Access / Collision Detection : méthode d'accès au média partagé Ethernet historique (half-duplex). _(Module 1, Topic 1.3)_\n\n## D {#sec-glossaire-d}\n\n**DAI (Dynamic ARP Inspection)** — Fonctionnalité de switch vérifiant chaque paquet ARP sur les ports untrusted en le comparant à la binding table DHCP snooping. _(Module 5, Topic 5.7)_\n\n**Data plane** — Plan de données (forwarding plane) : couche de transfert effectif des paquets selon les tables construites par le control plane. _(Module 6, Topic 6.3)_\n\n**Default route (route par défaut)** — Route catch-all correspondant à toute destination sans route plus spécifique : 0.0.0.0/0 (IPv4) ou ::/0 (IPv6). _(Module 3, Topic 3.3)_\n\n**DHCP (Dynamic Host Configuration Protocol)** — Protocole client-serveur (UDP 67/68) attribuant automatiquement une configuration IP complète aux clients. Processus en 4 étapes : DORA (Discover, Offer, Request, Acknowledge). _(Module 1, Topic 1.5 · Module 4, Topic 4.3/4.6)_\n\n**DHCP Relay** — Mécanisme convertissant les broadcasts DHCP en unicast pour atteindre un serveur DHCP dans un autre sous-réseau (commande `ip helper-address`). _(Module 4, Topic 4.6)_\n\n**DHCP Snooping** — Fonctionnalité de switch classifiant les ports en trusted/untrusted pour bloquer les serveurs DHCP non autorisés. _(Module 5, Topic 5.7)_\n\n**Diffie-Hellman** — Algorithme d'échange de clés permettant à deux pairs de s'accorder sur une clé partagée via un canal non sécurisé. _(Module 5, Topic 5.5)_\n\n**Distance administrative (AD)** — Entier (0-255) mesurant la confiance du routeur envers la source d'une route ; plus la valeur est basse, plus la source est fiable. _(Module 3, Topic 3.1/3.2)_\n\n**DNS (Domain Name System)** — Service de résolution de noms de domaine en adresses IP, utilisant UDP port 53 (requêtes) et TCP port 53 (transferts de zone). _(Module 1, Topic 1.5 · Module 4, Topic 4.3)_\n\n**DORA** — Les quatre étapes du processus d'attribution DHCP : Discover, Offer, Request, Acknowledge. _(Module 4, Topic 4.3)_\n\n**DR (Designated Router)** — Routeur élu sur un segment broadcast OSPF qui centralise l'échange de LSA, recevant les updates en 224.0.0.6. _(Module 3, Topic 3.4)_\n\n**DSCP (Differentiated Services Code Point)** — Champ de 6 bits dans l'en-tête IP (Layer 3) marquant la classe de service du paquet ; valeurs 0-63, préservé de bout en bout. _(Module 4, Topic 4.7)_\n\n**DTP (Dynamic Trunking Protocol)** — Protocole propriétaire Cisco négociant automatiquement le mode trunk/access entre deux ports de switch. _(Module 2, Topic 2.2)_\n\n**Dual-stack** — Configuration où une interface supporte simultanément IPv4 et IPv6. _(Module 1, Topic 1.8)_\n\n**Duplex mismatch** — Problème où un côté du lien est en full-duplex et l'autre en half-duplex, causant des late collisions et des CRC errors. _(Module 1, Topic 1.4)_\n\n## E {#sec-glossaire-e}\n\n**ECMP (Equal-Cost Multi-Path)** — Technique de routage répartissant le trafic sur plusieurs chemins de coût égal vers la même destination. _(Module 1, Topic 1.2 · Module 3, Topic 3.2)_\n\n**EF (Expedited Forwarding)** — Classe DSCP (valeur décimale 46) pour la voix, garantissant priorité maximale et latence minimale. _(Module 4, Topic 4.7)_\n\n**EIGRP (Enhanced Interior Gateway Routing Protocol)** — Protocole de routage hybride Cisco ; AD = 90 (interne) / 170 (externe), métrique composite (bande passante + délai). _(Module 3, Topic 3.1)_\n\n**Encapsulation** — Processus d'ajout d'en-têtes de protocole à chaque couche du modèle OSI lors de la transmission de données. _(Module 1, Topic 1.4)_\n\n**err-disabled** — État d'un port de switch désactivé automatiquement par une fonctionnalité de sécurité (BPDU Guard, port security, etc.). _(Module 2, Topic 2.5 · Module 5, Topic 5.7)_\n\n**ESP (Encapsulating Security Payload)** — Protocole IPsec (IP Protocol 50) fournissant chiffrement + intégrité + authentification ; le plus utilisé. _(Module 5, Topic 5.5)_\n\n**EtherChannel** — Technologie regroupant 2 à 8 liens physiques en un seul lien logique pour augmenter la bande passante et la redondance. _(Module 2, Topic 2.4)_\n\n**EUI-64 (Modified)** — Méthode de génération automatique de l'Interface ID IPv6 (64 bits) à partir de l'adresse MAC (48 bits) en insérant FF:FE et inversant le 7e bit. _(Module 1, Topic 1.9)_\n\n## F {#sec-glossaire-f}\n\n**Fabric** — Combinaison de l'overlay et de l'underlay orchestrée par le contrôleur SDN, désignant le réseau SDN complet. _(Module 6, Topic 6.3)_\n\n**FHRP (First Hop Redundancy Protocol)** — Famille de protocoles (HSRP, VRRP, GLBP) créant une IP virtuelle partagée entre routeurs pour la redondance de passerelle. _(Module 3, Topic 3.5)_\n\n**Fibre monomode (SMF)** — Fibre optique à cœur fin (9 µm), source laser, portée jusqu'à 80+ km. _(Module 1, Topic 1.3)_\n\n**Fibre multimode (MMF)** — Fibre optique à cœur large (50/62,5 µm), source LED/VCSEL, portée jusqu'à 550 m en 10G. _(Module 1, Topic 1.3)_\n\n**FlexConnect** — Mode AP hybride géré par le WLC mais capable de commuter le trafic localement ; survie en cas de perte du WLC. _(Module 2, Topic 2.6)_\n\n**Floating static route** — Route statique avec une AD volontairement augmentée pour servir de route de secours, invisible tant qu'une route dynamique préférable existe. _(Module 3, Topic 3.3)_\n\n**Flooding** — Envoi d'une trame sur tous les ports du même VLAN sauf le port source, pour les unknown unicast, broadcast et multicast. _(Module 1, Topic 1.13)_\n\n**FTP (File Transfer Protocol)** — Protocole de transfert de fichiers complet (TCP ports 20/21) avec authentification, mais credentials transmis en clair. _(Module 1, Topic 1.5 · Module 4, Topic 4.9)_\n\n**Full-duplex** — Mode de communication permettant l'émission et la réception simultanées sur un lien Ethernet. _(Module 1, Topic 1.3)_\n\n## G {#sec-glossaire-g}\n\n**Gateway of last resort** — Route par défaut active du routeur (0.0.0.0/0) ; si non configurée, les paquets sans route spécifique sont jetés. _(Module 3, Topic 3.1)_\n\n**GLBP (Gateway Load Balancing Protocol)** — Protocole FHRP propriétaire Cisco avec load balancing natif via MAC virtuelles multiples. _(Module 3, Topic 3.5)_\n\n**GRE (Generic Routing Encapsulation)** — Protocole de tunneling encapsulant des paquets multicast/non-IP ; souvent combiné avec IPsec pour les VPN site-to-site. _(Module 5, Topic 5.5 · Module 6, Topic 6.3)_\n\n**GUA (Global Unicast Address)** — Adresse IPv6 routable sur Internet (préfixe 2000::/3), équivalent des adresses publiques IPv4. _(Module 1, Topic 1.9)_\n\n## H {#sec-glossaire-h}\n\n**HSRP (Hot Standby Router Protocol)** — Protocole FHRP propriétaire Cisco ; rôles Active/Standby/Listen, préemption désactivée par défaut. _(Module 3, Topic 3.5)_\n\n**HTTP / HTTPS** — Protocoles web non chiffré (TCP 80) / chiffré TLS (TCP 443) ; HTTPS est aussi utilisé comme transport pour les APIs REST. _(Module 1, Topic 1.5 · Module 6, Topic 6.5)_\n\n**Hyperviseur** — Logiciel créant et gérant des machines virtuelles. Type 1 (bare-metal : ESXi, Hyper-V, KVM) ou Type 2 (hosted : VMware Workstation, VirtualBox). _(Module 1, Topic 1.12)_\n\n## I {#sec-glossaire-i}\n\n**IA générative** — Système d'intelligence artificielle capable de produire du contenu nouveau (configurations, analyses) à partir de prompts en langage naturel. _(Module 1, Topic 1.14)_\n\n**ICMP (Internet Control Message Protocol)** — Protocole de couche 3 utilisé pour les messages de diagnostic réseau (ping, traceroute). _(Module 1, Topic 1.10 · Module 3, Topic 3.3)_\n\n**Idempotence** — Propriété garantissant qu'exécuter une opération plusieurs fois produit toujours le même résultat, sans effet de bord supplémentaire. _(Module 6, Topic 6.6)_\n\n**IKE (Internet Key Exchange)** — Protocole de négociation IPsec en deux phases pour l'authentification et l'échange de clés sécurisés. _(Module 5, Topic 5.5)_\n\n**Intent-Based Networking (IBN)** — Gestion réseau automatisée où l'administrateur exprime une intention et le système la traduit en configuration technique. _(Module 1, Topic 1.1 · Module 6, Topic 6.4)_\n\n**IPS (Intrusion Prevention System)** — Système analysant le trafic en temps réel pour détecter et bloquer les attaques réseau connues. _(Module 1, Topic 1.1 · Module 5, Topic 5.1)_\n\n**IPsec** — Suite de protocoles de sécurité pour le chiffrement et l'authentification des paquets IP, utilisée dans les VPN site-to-site et remote access. _(Module 1, Topic 1.2 · Module 5, Topic 5.5)_\n\n**IPv4** — Protocole d'adressage réseau utilisant des adresses de 32 bits en notation décimale pointée (ex : 192.168.1.10). _(Module 1, Topic 1.6)_\n\n**IPv6** — Protocole d'adressage réseau utilisant des adresses de 128 bits en notation hexadécimale, remplaçant IPv4. _(Module 1, Topic 1.8)_\n\n## J {#sec-glossaire-j}\n\n**JSON (JavaScript Object Notation)** — Format de données léger et lisible, standard de facto pour les APIs REST et l'automatisation réseau. _(Module 6, Topic 6.7)_\n\n## K {#sec-glossaire-k}\n\n**Kubernetes** — Système d'orchestration de conteneurs gérant le déploiement, le scaling et la gestion de conteneurs à grande échelle. _(Module 1, Topic 1.12)_\n\n## L {#sec-glossaire-l}\n\n**LACP (Link Aggregation Control Protocol)** — Protocole standard IEEE 802.3ad de négociation d'EtherChannel avec modes active et passive. _(Module 2, Topic 2.4)_\n\n**Link-Local (FE80::/10)** — Adresse IPv6 valide uniquement sur le lien local, générée automatiquement, utilisée par les protocoles de routage. _(Module 1, Topic 1.9)_\n\n**Link-state** — Type de protocole de routage où chaque routeur possède une carte complète de la topologie et calcule ses routes indépendamment (OSPF, IS-IS). _(Module 3, Topic 3.4)_\n\n**LLDP (Link Layer Discovery Protocol)** — Protocole standard IEEE 802.1AB de découverte Layer 2, multi-vendeur, à activer manuellement sur les équipements Cisco. _(Module 2, Topic 2.3)_\n\n**Longest prefix match** — Règle fondamentale du routage IP : le routeur sélectionne toujours la route dont le masque est le plus long (le plus spécifique). _(Module 1, Topic 1.6 · Module 3, Topic 3.2)_\n\n**LSA (Link-State Advertisement)** — Unité d'information OSPF décrivant un lien ou un réseau, stockée dans la LSDB et échangée entre routeurs. _(Module 3, Topic 3.4)_\n\n**LSDB (Link-State Database)** — Base de données topologique OSPF contenant tous les LSA ; identique sur tous les routeurs d'une même area. _(Module 3, Topic 3.4)_\n\n## M {#sec-glossaire-m}\n\n**MAC (Media Access Control)** — Adresse physique de 48 bits identifiant de manière unique une interface réseau sur un segment L2. _(Module 1, Topic 1.1/1.13)_\n\n**MAC address table (CAM table)** — Table d'un switch associant les adresses MAC aux ports et VLANs, avec un aging time par défaut de 300 secondes. _(Module 1, Topic 1.13)_\n\n**Machine Learning (ML)** — Approche d'intelligence artificielle où les systèmes apprennent à partir de données pour détecter des anomalies et des menaces réseau. _(Module 5, Topic 5.11)_\n\n**MFA (Multi-Factor Authentication)** — Authentification multifacteur combinant au moins deux catégories : connaissance, possession, inhérence. _(Module 5, Topic 5.4)_\n\n**MIB (Management Information Base)** — Base de données hiérarchique en arbre contenant les variables supervisables d'un équipement SNMP (OIDs). _(Module 4, Topic 4.4)_\n\n**Modèle OSI** — Modèle de référence en 7 couches (physique, liaison, réseau, transport, session, présentation, application) pour la communication réseau. _(Module 1, Topic 1.1)_\n\n**MPLS (Multiprotocol Label Switching)** — Technologie WAN opérateur utilisant des labels pour acheminer les paquets avec des garanties de SLA. _(Module 1, Topic 1.2)_\n\n**MTU (Maximum Transmission Unit)** — Taille maximale d'un paquet transmissible sur un lien sans fragmentation (1500 octets par défaut en Ethernet). _(Module 1, Topic 1.4 · Module 3, Topic 3.4)_\n\n**Multicast** — Mode de transmission envoyant des paquets à un groupe spécifique d'adresses (ex : 224.0.0.5 pour OSPF, FF02::1 en IPv6). _(Module 1, Topic 1.9 · Module 3, Topic 3.4)_\n\n## N {#sec-glossaire-n}\n\n**NAT (Network Address Translation)** — Technique remplaçant les adresses IP privées par une adresse publique pour l'accès à Internet. _(Module 1, Topic 1.7 · Module 4, Topic 4.1)_\n\n**NBAR (Network-Based Application Recognition)** — Technologie Cisco de reconnaissance d'application au niveau Layer 7 pour la classification QoS. _(Module 4, Topic 4.7)_\n\n**NDP (Neighbor Discovery Protocol)** — Protocole IPv6 remplaçant ARP, assurant la découverte des voisins, l'auto-configuration et la détection de duplication (DAD). _(Module 1, Topic 1.9)_\n\n**NETCONF** — Protocole southbound API basé sur XML et SSH, utilisé pour configurer les équipements réseau de manière programmatique. _(Module 6, Topic 6.3)_\n\n**NetFlow** — Technologie Cisco exportant les métadonnées de flux réseau (source, destination, ports, octets) vers un collecteur pour analyse. _(Module 5, Topic 5.11)_\n\n**NGFW (Next-Generation Firewall)** — Pare-feu nouvelle génération inspectant le trafic jusqu'à la couche 7, avec détection de malwares et politiques basées sur l'identité. _(Module 1, Topic 1.1)_\n\n**Northbound API** — Interface entre les applications et le contrôleur SDN (vers le haut), typiquement REST/HTTP. _(Module 6, Topic 6.3)_\n\n**NTP (Network Time Protocol)** — Protocole de synchronisation horaire utilisant UDP port 123 avec une hiérarchie de stratum (0 = horloge atomique). _(Module 1, Topic 1.5 · Module 4, Topic 4.2)_\n\n## O {#sec-glossaire-o}\n\n**OID (Object Identifier)** — Identifiant numérique hiérarchique unique d'une variable dans la MIB SNMP (ex : 1.3.6.1.2.1.1.5 pour sysName). _(Module 4, Topic 4.4)_\n\n**OpenFlow** — Protocole southbound API originel du SDN, permettant au contrôleur de programmer directement les tables de forwarding des équipements. _(Module 6, Topic 6.3)_\n\n**OSPF (Open Shortest Path First)** — Protocole de routage link-state utilisant l'algorithme SPF (Dijkstra) ; AD = 110, métrique basée sur le coût (bande passante). _(Module 3, Topic 3.4)_\n\n**OSPFv3** — Version d'OSPF pour IPv6 (RFC 5340), utilisant les adresses link-local comme adresses de next-hop. _(Module 1, Topic 1.9 · Module 3, Topic 3.4)_\n\n**Overlay** — Réseau virtuel construit par-dessus le réseau physique via des tunnels (VXLAN, GRE, IPsec). _(Module 6, Topic 6.3)_\n\n**OWE (Opportunistic Wireless Encryption)** — Chiffrement automatique des réseaux Wi-Fi ouverts (sans mot de passe) introduit avec WPA3. _(Module 5, Topic 5.9)_\n\n## P {#sec-glossaire-p}\n\n**PAgP (Port Aggregation Protocol)** — Protocole propriétaire Cisco de négociation d'EtherChannel avec modes desirable et auto. _(Module 2, Topic 2.4)_\n\n**passive-interface** — Commande OSPF empêchant l'envoi de Hello sur une interface tout en annonçant son réseau aux voisins. _(Module 3, Topic 3.4)_\n\n**PAT (Port Address Translation)** — NAT overload : tous les hôtes internes partagent une seule adresse publique, distingués par numéros de port source. _(Module 4, Topic 4.1)_\n\n**PHB (Per-Hop Behavior)** — Comportement de traitement QoS appliqué indépendamment par chaque équipement réseau à chaque saut. _(Module 4, Topic 4.7)_\n\n**PKI (Public Key Infrastructure)** — Infrastructure à clés publiques gérant les certificats numériques (émission, révocation, renouvellement). _(Module 5, Topic 5.4)_\n\n**PMF (Protected Management Frames)** — Protection des trames de gestion Wi-Fi ; optionnel en WPA2, obligatoire en WPA3. _(Module 5, Topic 5.9)_\n\n**PnP (Plug and Play)** — Mécanisme Cisco d'onboarding automatique des équipements réseau via DNA Center, sans configuration manuelle préalable. _(Module 6, Topic 6.4)_\n\n**PoE (Power over Ethernet)** — Technologie permettant d'alimenter un appareil réseau via le câble Ethernet. Standards : 802.3af (15,4 W), 802.3at/PoE+ (30 W), 802.3bt (60-90 W). _(Module 1, Topic 1.1 · Module 2, Topic 2.7)_\n\n**Policy-map** — Objet de configuration IOS définissant les actions QoS (marquage, queuing, policing) à appliquer aux classes de trafic. _(Module 4, Topic 4.7)_\n\n**Port-Channel** — Interface logique représentant un EtherChannel ; STP la traite comme un port unique. _(Module 2, Topic 2.4)_\n\n**PortFast** — Fonctionnalité STP permettant à un port d'accès de passer immédiatement en Forwarding sans attendre la convergence. _(Module 2, Topic 2.5)_\n\n**Port Security** — Fonctionnalité de switch limitant le nombre d'adresses MAC autorisées par port pour prévenir le MAC flooding. _(Module 1, Topic 1.13 · Module 5, Topic 5.7)_\n\n**PSK (Pre-Shared Key)** — Mode d'authentification avec un mot de passe partagé entre tous les utilisateurs (Wi-Fi Personal, IPsec). _(Module 1, Topic 1.11 · Module 5, Topic 5.5)_\n\n**Puppet** — Outil de gestion de configuration agent-based utilisant le modèle pull, des manifests en DSL propriétaire et un Puppet Master. _(Module 6, Topic 6.6)_\n\n## Q {#sec-glossaire-q}\n\n**QoS (Quality of Service)** — Ensemble de mécanismes priorisant certains types de trafic réseau (classification, marquage, queuing, policing, shaping). _(Module 4, Topic 4.7)_\n\n## R {#sec-glossaire-r}\n\n**RADIUS (Remote Authentication Dial-In User Service)** — Protocole AAA standard (UDP 1812/1813) ne chiffrant que le mot de passe, combinant Auth+Authz ; utilisé pour Wi-Fi/VPN/802.1X. _(Module 2, Topic 2.8 · Module 5, Topic 5.8)_\n\n**Rapid PVST+** — Version améliorée de STP par défaut sur les switches Cisco : convergence rapide (1-2 s) et un arbre STP distinct par VLAN. _(Module 2, Topic 2.5)_\n\n**REST (Representational State Transfer)** — Style d'architecture pour les services web utilisant HTTP comme protocole de communication (stateless, URI, verbes HTTP). _(Module 6, Topic 6.5)_\n\n**RESTCONF** — API RESTful combinant les principes REST (HTTP) avec les modèles de données YANG de NETCONF. _(Module 6, Topic 6.3)_\n\n**RFC 1918** — Standard définissant les trois plages d'adresses IPv4 privées non routables (10.0.0.0/8, 172.16.0.0/12, 192.168.0.0/16). _(Module 1, Topic 1.7)_\n\n**RIP (Routing Information Protocol)** — Protocole de routage distance-vector ; AD = 120, métrique = hop count (maximum 15 sauts). _(Module 3, Topic 3.1)_\n\n**Root bridge** — Switch élu comme racine de l'arbre STP, ayant le Bridge ID le plus bas ; tous ses ports sont Designated. _(Module 2, Topic 2.5)_\n\n**Root Port (RP)** — Port sur un switch non-root ayant le meilleur chemin (coût le plus bas) vers le root bridge ; un seul par switch. _(Module 2, Topic 2.5)_\n\n**Router ID (RID)** — Identifiant unique de 32 bits au format IPv4 pour chaque routeur OSPF. Priorité : commande `router-id` > IP loopback la plus haute > IP physique la plus haute. _(Module 3, Topic 3.4)_\n\n**Router-on-a-stick** — Méthode de routage inter-VLAN utilisant un seul lien trunk entre le switch et le routeur, avec des sous-interfaces dot1Q. _(Module 2, Topic 2.1 · Module 3, Topic 3.4)_\n\n**RSA** — Algorithme de chiffrement asymétrique utilisé pour générer les clés SSH (minimum 2048 bits recommandé). _(Module 2, Topic 2.8 · Module 5, Topic 5.5)_\n\n## S {#sec-glossaire-s}\n\n**SAE (Simultaneous Authentication of Equals)** — Mécanisme d'authentification WPA3 remplaçant PSK, résistant aux attaques par dictionnaire offline. _(Module 1, Topic 1.11 · Module 5, Topic 5.9)_\n\n**SD-Access** — Solution SDN Cisco de campus utilisant DNA Center, LISP, VXLAN et TrustSec pour la fabric. _(Module 6, Topic 6.3)_\n\n**SD-WAN (Software-Defined WAN)** — Architecture SDN pour les réseaux étendus, utilisant vManage comme contrôleur et IPsec pour l'overlay. _(Module 1, Topic 1.2 · Module 6, Topic 6.3)_\n\n**SDN (Software-Defined Networking)** — Architecture réseau où le control plane est centralisé sur un contrôleur, séparant les décisions de l'acheminement du trafic. _(Module 6, Topic 6.3)_\n\n**Shaping** — Mécanisme QoS retardant (buffer) les paquets pour lisser le débit de sortie ; applicable uniquement en sortie. _(Module 4, Topic 4.7)_\n\n**show ip interface brief** — Commande Cisco affichant un résumé de toutes les interfaces avec leur adresse IP et leur statut (up/down). _(Module 1, Topic 1.6)_\n\n**show ip ospf neighbor** — Commande CLI affichant les voisins OSPF avec leur Router ID, priorité, état, dead time, adresse et interface. _(Module 3, Topic 3.4)_\n\n**show ip route** — Commande Cisco affichant la table de routage IPv4 complète avec codes, préfixes, masques, next-hops et métriques. _(Module 3, Topic 3.1)_\n\n**show mac address-table** — Commande Cisco affichant toute la table d'adresses MAC du switch avec les VLANs et ports associés. _(Module 1, Topic 1.13)_\n\n**show spanning-tree** — Commande affichant l'état STP pour un VLAN : root bridge, bridge local, rôles et états de chaque port. _(Module 2, Topic 2.5)_\n\n**show vlan brief** — Commande de vérification affichant la liste des VLANs, leur nom, statut et ports associés. _(Module 2, Topic 2.1)_\n\n**SLAAC (Stateless Address Autoconfiguration)** — Mécanisme IPv6 d'auto-configuration des adresses sans serveur DHCP, basé sur le préfixe annoncé par le routeur. _(Module 1, Topic 1.8)_\n\n**SNMP (Simple Network Management Protocol)** — Protocole de supervision réseau (UDP 161/162). Versions : v1/v2c (community strings en clair), v3 (authentification + chiffrement). _(Module 1, Topic 1.5 · Module 4, Topic 4.4)_\n\n**SOHO (Small Office / Home Office)** — Architecture réseau simplifiée avec un seul appareil multifonction (routeur/switch/Wi-Fi/NAT/DHCP). _(Module 1, Topic 1.2)_\n\n**Southbound API** — Interface entre le contrôleur SDN et les équipements réseau (vers le bas), typiquement NETCONF, RESTCONF, OpenFlow. _(Module 6, Topic 6.3)_\n\n**Spine-Leaf** — Architecture de datacenter garantissant un nombre de hops constant (2) entre serveurs, optimisée pour le trafic est-ouest. _(Module 1, Topic 1.2)_\n\n**SPF (Shortest Path First / Dijkstra)** — Algorithme utilisé par OSPF pour calculer le chemin le plus court vers chaque destination dans la topologie. _(Module 3, Topic 3.4)_\n\n**SSH (Secure Shell)** — Protocole d'accès distant sécurisé (chiffré) utilisant TCP port 22, remplaçant Telnet. SSHv2 est le standard. _(Module 1, Topic 1.5 · Module 4, Topic 4.8)_\n\n**SSID (Service Set Identifier)** — Nom du réseau Wi-Fi visible par les clients ; un AP peut diffuser plusieurs SSID. _(Module 1, Topic 1.11 · Module 2, Topic 2.9)_\n\n**STP (Spanning Tree Protocol)** — Protocole de couche 2 empêchant les boucles en désactivant logiquement certains liens redondants. _(Module 1, Topic 1.13 · Module 2, Topic 2.5)_\n\n**Stratum (NTP)** — Niveau hiérarchique NTP indiquant la distance à la source de référence ; 0 = horloge atomique, 16 = non synchronisé. _(Module 4, Topic 4.2)_\n\n**Subnetting** — Technique de découpage d'un réseau en sous-réseaux en empruntant des bits de la partie hôte. _(Module 1, Topic 1.6)_\n\n**SVI (Switch Virtual Interface)** — Interface virtuelle sur un switch L3 associée à un VLAN, servant de passerelle par défaut pour ce VLAN. _(Module 1, Topic 1.1 · Module 2, Topic 2.1)_\n\n**Syslog** — Standard de journalisation réseau (RFC 5424, UDP 514). Niveaux de sévérité de 0 (Emergency) à 7 (Debugging). _(Module 1, Topic 1.5 · Module 4, Topic 4.5)_\n\n## T {#sec-glossaire-t}\n\n**TACACS+** — Protocole AAA propriétaire Cisco (TCP 49) chiffrant le paquet entier, avec séparation Auth/Authz/Acct et autorisation par commande. _(Module 2, Topic 2.8 · Module 5, Topic 5.8)_\n\n**TCP (Transmission Control Protocol)** — Protocole de transport fiable orienté connexion avec accusé de réception, numéros de séquence et contrôle de flux (couche 4). _(Module 1, Topic 1.5)_\n\n**TFTP (Trivial File Transfer Protocol)** — Protocole de transfert de fichiers minimaliste (UDP port 69) sans authentification ; utilisé pour les mises à jour IOS et sauvegardes. _(Module 1, Topic 1.5 · Module 4, Topic 4.9)_\n\n**Three-tier** — Architecture réseau à trois couches (accès, distribution, cœur) pour les grands campus (>500 utilisateurs). _(Module 1, Topic 1.2)_\n\n**Three-way handshake** — Processus d'établissement de connexion TCP en trois étapes : SYN, SYN-ACK, ACK. _(Module 1, Topic 1.5)_\n\n**TLS (Transport Layer Security)** — Protocole de chiffrement assurant la confidentialité des communications HTTPS, SSH et VPN SSL. _(Module 2, Topic 2.8 · Module 5, Topic 5.11)_\n\n**Trunk (port trunk)** — Port de switch transportant les trames de plusieurs VLANs sur un seul lien physique, grâce au tagging 802.1Q. _(Module 2, Topic 2.2)_\n\n**Two-tier (Collapsed Core)** — Architecture réseau à deux niveaux combinant distribution et cœur, adaptée aux campus de petite/moyenne taille. _(Module 1, Topic 1.2)_\n\n## U {#sec-glossaire-u}\n\n**UDP (User Datagram Protocol)** — Protocole de transport sans connexion, rapide et à faible overhead (8 octets d'en-tête), sans fiabilité intégrée (couche 4). _(Module 1, Topic 1.5)_\n\n**ULA (Unique Local Address)** — Adresse IPv6 privée non routable (préfixe FC00::/7), équivalent de RFC 1918 en IPv4. _(Module 1, Topic 1.9)_\n\n**Underlay** — Réseau physique sous-jacent (câbles, switches, routeurs) fournissant la connectivité IP de base pour le transport overlay. _(Module 6, Topic 6.3)_\n\n## V {#sec-glossaire-v}\n\n**VLAN (Virtual LAN)** — Réseau local virtuel segmentant logiquement un switch en plusieurs domaines de broadcast indépendants. _(Module 1, Topic 1.13 · Module 2, Topic 2.1)_\n\n**VLAN natif (native VLAN)** — VLAN dont les trames traversent le trunk sans tag 802.1Q ; par défaut VLAN 1. Un mismatch entre extrémités cause des erreurs. _(Module 2, Topic 2.2)_\n\n**VLSM (Variable-Length Subnet Masking)** — Technique de subnetting utilisant des masques de longueurs différentes pour optimiser l'espace d'adressage. _(Module 1, Topic 1.6 · Module 3, Topic 3.4)_\n\n**VPN (Virtual Private Network)** — Tunnel chiffré établi sur un réseau public pour sécuriser les communications. Types : site-to-site (IPsec) et remote access (SSL/AnyConnect). _(Module 1, Topic 1.2 · Module 5, Topic 5.5)_\n\n**VRF (Virtual Routing and Forwarding)** — Virtualisation de la table de routage permettant à un seul routeur de maintenir plusieurs tables indépendantes et isolées. _(Module 1, Topic 1.12 · Module 6, Topic 6.3)_\n\n**VRRP (Virtual Router Redundancy Protocol)** — Protocole FHRP standard IETF (RFC 5798) ; rôles Master/Backup, préemption activée par défaut. _(Module 3, Topic 3.5)_\n\n**VTY (Virtual Terminal Line)** — Ligne virtuelle sur un équipement Cisco permettant les connexions distantes SSH/Telnet ; typiquement 0-15. _(Module 2, Topic 2.8 · Module 4, Topic 4.8)_\n\n**VXLAN (Virtual Extensible LAN)** — Technologie d'encapsulation overlay étendant les VLANs à travers un réseau IP (underlay), utilisée par SD-Access. _(Module 6, Topic 6.3)_\n\n## W {#sec-glossaire-w}\n\n**WAN (Wide Area Network)** — Réseau étendu connectant des sites géographiquement dispersés via MPLS, VPN, SD-WAN ou Metro Ethernet. _(Module 1, Topic 1.2)_\n\n**Wildcard mask** — Masque inversé du masque de sous-réseau, utilisé dans les ACL et les configurations OSPF (ex : 0.0.0.255 = /24). _(Module 3, Topic 3.4 · Module 5, Topic 5.6)_\n\n**WLC (Wireless LAN Controller)** — Contrôleur centralisant la gestion de tous les AP lightweight (SSID, sécurité, canaux, puissance, roaming). _(Module 1, Topic 1.1 · Module 2, Topic 2.6)_\n\n**WPA2** — Standard de sécurité Wi-Fi utilisant AES-CCMP 128 bits. Modes : Personal (PSK) et Enterprise (802.1X/RADIUS). _(Module 1, Topic 1.11 · Module 5, Topic 5.9)_\n\n**WPA3** — Dernier standard de sécurité Wi-Fi utilisant AES-GCMP et SAE, avec PMF obligatoire et OWE pour les réseaux ouverts. _(Module 1, Topic 1.11 · Module 5, Topic 5.9)_\n\n**WRED (Weighted Random Early Detection)** — Mécanisme d'évitement de congestion rejetant aléatoirement des paquets avant saturation de file, basé sur la probabilité de drop. _(Module 4, Topic 4.7)_\n\n## X-Z {#sec-glossaire-xz}\n\n**XML (eXtensible Markup Language)** — Format de données structuré avec balises, utilisé historiquement par SOAP et NETCONF pour la configuration réseau. _(Module 6, Topic 6.7)_\n\n**YAML** — Format de sérialisation de données lisible par l'humain, utilisé par les playbooks Ansible pour définir les tâches d'automatisation. _(Module 6, Topic 6.6)_\n\n**Zero-Touch Provisioning (ZTP)** — Mécanisme de déploiement automatique où un équipement neuf se configure en contactant le cloud, sans intervention humaine. _(Module 2, Topic 2.8 · Module 3, Topic 3.6)_\n"},"formats":{"pdf":{"identifier":{"display-name":"PDF","target-format":"pdf","base-format":"pdf"},"execute":{"fig-width":5.5,"fig-height":3.5,"fig-format":"pdf","fig-dpi":300,"df-print":"default","error":false,"eval":true,"cache":null,"freeze":false,"echo":true,"output":true,"warning":true,"include":true,"keep-md":false,"keep-ipynb":false,"ipynb":null,"enabled":null,"daemon":null,"daemon-restart":false,"debug":false,"ipynb-filters":[],"ipynb-shell-interactivity":null,"plotly-connected":true,"engine":"markdown"},"render":{"keep-tex":false,"keep-typ":false,"keep-source":false,"keep-hidden":false,"prefer-html":false,"output-divs":true,"output-ext":"pdf","fig-align":"default","fig-pos":null,"fig-env":null,"code-fold":"none","code-overflow":"scroll","code-link":false,"code-line-numbers":false,"code-tools":false,"tbl-colwidths":true,"merge-includes":true,"inline-includes":false,"preserve-yaml":false,"latex-auto-mk":true,"latex-auto-install":true,"latex-clean":true,"latex-min-runs":1,"latex-max-runs":10,"latex-makeindex":"makeindex","latex-makeindex-opts":[],"latex-tlmgr-opts":[],"latex-input-paths":[],"latex-output-dir":null,"link-external-icon":false,"link-external-newwindow":false,"self-contained-math":false,"format-resources":[]},"pandoc":{"pdf-engine":"lualatex","standalone":true,"variables":{"graphics":true,"tables":true},"default-image-extension":"pdf","to":"pdf","toc":true,"toc-depth":3,"number-sections":true,"highlight-style":"tango","output-file":"10-glossaire.pdf"},"language":{"toc-title-document":"Table of contents","toc-title-website":"On this page","related-formats-title":"Other Formats","related-notebooks-title":"Notebooks","source-notebooks-prefix":"Source","other-links-title":"Other Links","code-links-title":"Code Links","launch-dev-container-title":"Launch Dev Container","launch-binder-title":"Launch Binder","article-notebook-label":"Article Notebook","notebook-preview-download":"Download Notebook","notebook-preview-download-src":"Download Source","notebook-preview-back":"Back to Article","manuscript-meca-bundle":"MECA Bundle","section-title-abstract":"Abstract","section-title-appendices":"Appendices","section-title-footnotes":"Footnotes","section-title-references":"References","section-title-reuse":"Reuse","section-title-copyright":"Copyright","section-title-citation":"Citation","appendix-attribution-cite-as":"For attribution, please cite this work as:","appendix-attribution-bibtex":"BibTeX citation:","appendix-view-license":"View License","title-block-author-single":"Author","title-block-author-plural":"Authors","title-block-affiliation-single":"Affiliation","title-block-affiliation-plural":"Affiliations","title-block-published":"Published","title-block-modified":"Modified","title-block-keywords":"Keywords","callout-tip-title":"Tip","callout-note-title":"Note","callout-warning-title":"Warning","callout-important-title":"Important","callout-caution-title":"Caution","code-summary":"Code","code-tools-menu-caption":"Code","code-tools-show-all-code":"Show All Code","code-tools-hide-all-code":"Hide All Code","code-tools-view-source":"View Source","code-tools-source-code":"Source Code","tools-share":"Share","tools-download":"Download","code-line":"Line","code-lines":"Lines","copy-button-tooltip":"Copy to Clipboard","copy-button-tooltip-success":"Copied!","repo-action-links-edit":"Edit this page","repo-action-links-source":"View source","repo-action-links-issue":"Report an issue","back-to-top":"Back to top","search-no-results-text":"No results","search-matching-documents-text":"matching documents","search-copy-link-title":"Copy link to search","search-hide-matches-text":"Hide additional matches","search-more-match-text":"more match in this document","search-more-matches-text":"more matches in this document","search-clear-button-title":"Clear","search-text-placeholder":"","search-detached-cancel-button-title":"Cancel","search-submit-button-title":"Submit","search-label":"Search","toggle-section":"Toggle section","toggle-sidebar":"Toggle sidebar navigation","toggle-dark-mode":"Toggle dark mode","toggle-reader-mode":"Toggle reader mode","toggle-navigation":"Toggle navigation","crossref-fig-title":"Figure","crossref-tbl-title":"Table","crossref-lst-title":"Listing","crossref-thm-title":"Theorem","crossref-lem-title":"Lemma","crossref-cor-title":"Corollary","crossref-prp-title":"Proposition","crossref-cnj-title":"Conjecture","crossref-def-title":"Definition","crossref-exm-title":"Example","crossref-exr-title":"Exercise","crossref-ch-prefix":"Chapter","crossref-apx-prefix":"Appendix","crossref-sec-prefix":"Section","crossref-eq-prefix":"Equation","crossref-lof-title":"List of Figures","crossref-lot-title":"List of Tables","crossref-lol-title":"List of Listings","environment-proof-title":"Proof","environment-remark-title":"Remark","environment-solution-title":"Solution","listing-page-order-by":"Order By","listing-page-order-by-default":"Default","listing-page-order-by-date-asc":"Oldest","listing-page-order-by-date-desc":"Newest","listing-page-order-by-number-desc":"High to Low","listing-page-order-by-number-asc":"Low to High","listing-page-field-date":"Date","listing-page-field-title":"Title","listing-page-field-description":"Description","listing-page-field-author":"Author","listing-page-field-filename":"File Name","listing-page-field-filemodified":"Modified","listing-page-field-subtitle":"Subtitle","listing-page-field-readingtime":"Reading Time","listing-page-field-wordcount":"Word Count","listing-page-field-categories":"Categories","listing-page-minutes-compact":"{0} min","listing-page-category-all":"All","listing-page-no-matches":"No matching items","listing-page-words":"{0} words","listing-page-filter":"Filter","draft":"Draft"},"metadata":{"block-headings":true,"engines":[{"path":"C:\\Users\\madko\\AppData\\Local\\Programs\\Quarto\\share\\extension-subtrees\\julia-engine\\_extensions\\julia-engine\\julia-engine.js"}],"documentclass":"report","papersize":"a4","fontsize":"11pt","geometry":"margin=2.2cm","colorlinks":true,"linkcolor":"NavyBlue","urlcolor":"RoyalBlue","title":"Glossaire CCNA 200-301","description":"Environ 220 termes — protocoles, commandes, acronymes et concepts clés classés par ordre alphabétique"},"extensions":{"book":{"selfContainedOutput":true}}}},"projectFormats":["pdf"]}